paninipy/__init__.py
paninipy/cli.py
paninipy/community_regionalization/__init__.py
paninipy/community_regionalization/greedy_algorithm.py
paninipy/distributional_regionalization/__init__.py
paninipy/distributional_regionalization/functions.py
paninipy/hub_identification/__init__.py
paninipy/hub_identification/functions.py
paninipy/hypergraph_binning/__init__.py
paninipy/hypergraph_binning/functions.py
paninipy/mdl_backboning/__init__.py
paninipy/mdl_backboning/functions.py
paninipy/partial_rankings/__init__.py
paninipy/partial_rankings/functions.py
paninipy/partial_rankings/preprocessing.py
paninipy/population_clustering/__init__.py
paninipy/population_clustering/functions.py
paninipy-1.8.dist-info/licenses/LICENSE.txt
paninipy-1.8.dist-info/METADATA
paninipy-1.8.dist-info/WHEEL
paninipy-1.8.dist-info/entry_points.txt
paninipy-1.8.dist-info/top_level.txt
paninipy-1.8.dist-info/RECORD
