Metadata-Version: 2.4
Name: paninipy
Version: 1.8
Summary: Package of Algorithms for Nonparametric Inference with Networks in Python
Home-page: https://paninipy.readthedocs.io/en/latest/index.html
Author: Baiyue He, Alec Kirkley
Author-email: baiyue.he@connect.hku.hk, akirkley@hku.hk
License: The MIT License
Project-URL: Documentation, https://paninipy.readthedocs.io/en/latest/index.html
Project-URL: Source, https://paninipy.readthedocs.io/en/latest/index.html
Requires-Python: >=3.9
License-File: LICENSE.txt
Requires-Dist: numpy>=1.24
Requires-Dist: pandas>=2.2
Requires-Dist: scipy>=1.10
Requires-Dist: ray>=2.40.0
Dynamic: author
Dynamic: author-email
Dynamic: description
Dynamic: description-content-type
Dynamic: home-page
Dynamic: license
Dynamic: license-file
Dynamic: project-url
Dynamic: requires-dist
Dynamic: requires-python
Dynamic: summary
